starlight_protocol/__init__.py
starlight_protocol/sentinel_base.py
starlight_protocol-1.3.4.dist-info/licenses/LICENSE
starlight_protocol-1.3.4.dist-info/METADATA
starlight_protocol-1.3.4.dist-info/WHEEL
starlight_protocol-1.3.4.dist-info/top_level.txt
starlight_protocol-1.3.4.dist-info/RECORD
