Metadata-Version: 2.4
Name: starlight-protocol
Version: 1.3.4
Summary: Python SDK for the Starlight Protocol - Resilient browser automation through autonomous Sentinels
Author-email: Dhiraj Das <dhirajdas.666@gmail.com>
License: MIT
Project-URL: Homepage, https://github.com/starlight-protocol/starlight-python
Project-URL: Documentation, https://starlight-protocol.github.io/docs
Project-URL: Repository, https://github.com/starlight-protocol/starlight-python
Project-URL: Issues, https://github.com/starlight-protocol/starlight-python/issues
Project-URL: Changelog, https://github.com/starlight-protocol/starlight-python/blob/main/CHANGELOG.md
Project-URL: Author, https://dhirajdas.dev
Keywords: automation,testing,browser,selenium,playwright,sentinel,protocol,websocket,json-rpc
Classifier: Development Status :: 4 - Beta
Classifier: Intended Audience :: Developers
Classifier: License :: OSI Approved :: MIT License
Classifier: Operating System :: OS Independent
Classifier: Programming Language :: Python :: 3
Classifier: Programming Language :: Python :: 3.8
Classifier: Programming Language :: Python :: 3.9
Classifier: Programming Language :: Python :: 3.10
Classifier: Programming Language :: Python :: 3.11
Classifier: Programming Language :: Python :: 3.12
Classifier: Topic :: Software Development :: Testing
Classifier: Topic :: Software Development :: Quality Assurance
Requires-Python: >=3.8
License-File: LICENSE
Requires-Dist: websockets>=10.0
Provides-Extra: dev
Requires-Dist: pytest>=7.0; extra == "dev"
Requires-Dist: pytest-asyncio>=0.20; extra == "dev"
Requires-Dist: black; extra == "dev"
Requires-Dist: isort; extra == "dev"
Dynamic: license-file
